qcg/pilotjob/_version.py
qcg/pilotjob/allocation.py
qcg/pilotjob/client_cmd.py
qcg/pilotjob/command_line.py
qcg/pilotjob/config.py
qcg/pilotjob/environment.py
qcg/pilotjob/errors.py
qcg/pilotjob/executionjob.py
qcg/pilotjob/executionschema.py
qcg/pilotjob/executor.py
qcg/pilotjob/fileinterface.py
qcg/pilotjob/iterscheduler.py
qcg/pilotjob/joblist.py
qcg/pilotjob/localres.py
qcg/pilotjob/logger.py
qcg/pilotjob/manager.py
qcg/pilotjob/parseres.py
qcg/pilotjob/partitions.py
qcg/pilotjob/profile.py
qcg/pilotjob/publisher.py
qcg/pilotjob/receiver.py
qcg/pilotjob/reports.py
qcg/pilotjob/request.py
qcg/pilotjob/resources.py
qcg/pilotjob/response.py
qcg/pilotjob/resume.py
qcg/pilotjob/scheduler.py
qcg/pilotjob/scheduleralgo.py
qcg/pilotjob/service.py
qcg/pilotjob/slurmres.py
qcg/pilotjob/zmqinterface.py
qcg/pilotjob/api/__init__.py
qcg/pilotjob/api/errors.py
qcg/pilotjob/api/job.py
qcg/pilotjob/api/jobinfo.py
qcg/pilotjob/api/manager.py
qcg/pilotjob/launcher/__init__.py
qcg/pilotjob/launcher/agent.py
qcg/pilotjob/launcher/launcher.py
qcg/pilotjob/launcher/procstats.py
qcg/pilotjob/launcher/rtstats.py
qcg/pilotjob/utils/__init__.py
qcg/pilotjob/utils/auxdir.py
qcg/pilotjob/utils/proc_traces.py
qcg/pilotjob/utils/processes.py
qcg/pilotjob/utils/reportstats.py
qcg/pilotjob/utils/slurmenvresources.py
qcg/pilotjob/utils/util.py
qcg_pilotjob-0.14.2.dist-info/METADATA
qcg_pilotjob-0.14.2.dist-info/WHEEL
qcg_pilotjob-0.14.2.dist-info/entry_points.txt
qcg_pilotjob-0.14.2.dist-info/top_level.txt
qcg_pilotjob-0.14.2.dist-info/RECORD
