Metadata-Version: 2.4
Name: qcg-pilotjob
Version: 0.14.2
Summary: Manage many jobs inside one allocation
Home-page: http://github.com/vecma-project/QCG-PilotJob
Author: Piotr Kopta
Author-email: pkopta@man.poznan.pl
Requires-Dist: pyzmq
Requires-Dist: click
Requires-Dist: psutil
Dynamic: author
Dynamic: author-email
Dynamic: description
Dynamic: description-content-type
Dynamic: home-page
Dynamic: requires-dist
Dynamic: summary
